__init__.py
pySubnetSB/__init__.py
pySubnetSB/api.py
pySubnetSB/assignment_evaluator.py
pySubnetSB/assignment_evaluator_worker.py
pySubnetSB/assignment_pair.py
pySubnetSB/benchmark.py
pySubnetSB/benchmark_runner.py
pySubnetSB/checkpoint_manager.py
pySubnetSB/cluster_builder.py
pySubnetSB/compatibility_collection.py
pySubnetSB/constants.py
pySubnetSB/constraint.py
pySubnetSB/constraint_option_collection.py
pySubnetSB/identity_hash_benchmark.py
pySubnetSB/make_antimony.py
pySubnetSB/matrix.py
pySubnetSB/mock_queue.py
pySubnetSB/model_serializer.py
pySubnetSB/named_matrix.py
pySubnetSB/network.py
pySubnetSB/network_base.py
pySubnetSB/network_collection.py
pySubnetSB/parallel_subnet_finder.py
pySubnetSB/parallel_subnet_finder_worker.py
pySubnetSB/performance_monitor.py
pySubnetSB/processed_network.py
pySubnetSB/processed_network_collection.py
pySubnetSB/reaction_constraint.py
pySubnetSB/significance_calculator.py
pySubnetSB/significance_calculator_core.py
pySubnetSB/species_constraint.py
pySubnetSB/stoichometry.py
pySubnetSB/subnet_finder.py
pySubnetSB/subnet_finder_workunit_manager.py
pySubnetSB/util.py
pySubnetSB/worker_checkpoint_manager.py
pySubnetSB_tests/__init__.py
pySubnetSB_tests/test_api.py
pySubnetSB_tests/test_assignment_evaluator_worker.py
pySubnetSB_tests/test_assignment_pair.py
pySubnetSB_tests/test_benchmark.py
pySubnetSB_tests/test_checkpoint_manager.py
pySubnetSB_tests/test_cluster_builder.py
pySubnetSB_tests/test_compatibility_collection.py
pySubnetSB_tests/test_constraint.py
pySubnetSB_tests/test_constraint_option_collection.py
pySubnetSB_tests/test_identity_hash_benchmark.py
pySubnetSB_tests/test_matrix.py
pySubnetSB_tests/test_model_serializer.py
pySubnetSB_tests/test_named_matrix.py
pySubnetSB_tests/test_network.py
pySubnetSB_tests/test_network_base.py
pySubnetSB_tests/test_network_collection.py
pySubnetSB_tests/test_parallel_subnet_finder.py
pySubnetSB_tests/test_parallel_subnet_finder_worker.py
pySubnetSB_tests/test_processed_network.py
pysubnetsb-1.0.9.dist-info/licenses/LICENSE
pysubnetsb-1.0.9.dist-info/METADATA
pysubnetsb-1.0.9.dist-info/WHEEL
pysubnetsb-1.0.9.dist-info/top_level.txt
pysubnetsb-1.0.9.dist-info/RECORD
