Metadata-Version: 2.4
Name: pySubnetSB
Version: 1.0.9
Summary: Python Subnet Discovery for Systems Biology
Author-email: Joseph Hellerstein <joseph.hellerstein@gmail.com>
License: MIT License
Project-URL: Homepage, https://github.com/ModelEngineering/pySubnetSB
Requires-Python: >=3.9
License-File: LICENSE
Requires-Dist: numpy
Requires-Dist: build
Requires-Dist: coverage
Requires-Dist: jupyterlab
Requires-Dist: matplotlib
Requires-Dist: nose2
Requires-Dist: pandas
Requires-Dist: pip>20
Requires-Dist: pylint
Requires-Dist: python-libsbml
Requires-Dist: sbmlnetwork
Requires-Dist: seaborn
Requires-Dist: simplesbml
Requires-Dist: tellurium
Requires-Dist: tqdm
Requires-Dist: twine
Requires-Dist: zipfile36
Dynamic: license-file
